ShaderFlow/__init__.py
shaderflow-2024.1.15.dist-info/METADATA
shaderflow-2024.1.15.dist-info/WHEEL
shaderflow-2024.1.15.dist-info/RECORD
